actsecmodel/__init__.py
actsecmodel/actsecmodel.py
actsecmodel-0.0.3.dist-info/METADATA
actsecmodel-0.0.3.dist-info/WHEEL
actsecmodel-0.0.3.dist-info/licenses/LICENSE.txt
actsecmodel-0.0.3.dist-info/RECORD
