Metadata-Version: 2.1
Name: actsecmodel
Version: 0.0.3
Summary: A package designed to be used to research the development of multilayer Reddit discussion networks
Author-email: Aiden Littlewood-Johnson <aidenlittlewoodjohnson@gmail.com>
License-File: LICENSE.txt
Classifier: License :: OSI Approved :: MIT License
Classifier: Operating System :: OS Independent
Classifier: Programming Language :: Python :: 3
Requires-Python: >=3.7
